<?xml version="1.0" encoding="utf-8"?>
	<annotation>
		<folder>driving_annotation_dataset</folder>
		<filename>1177.jpg</filename>
		<size>
			<width>1024</width>
			<height>576</height>
			<depth>3</depth>
		</size>
		<object>
			<name>face</name>
			<pose>Unspecified</pose>
			<truncated>0</truncated>
			<difficult>0</difficult>
			<bndbox>
				<xmin>511</xmin>
				<ymin>2</ymin>
				<xmax>589</xmax>
				<ymax>103</ymax>
			</bndbox>
		</object>
		<object>
			<name>face</name>
			<pose>Unspecified</pose>
			<truncated>0</truncated>
			<difficult>0</difficult>
			<bndbox>
				<xmin>734</xmin>
				<ymin>2</ymin>
				<xmax>846</xmax>
				<ymax>119</ymax>
			</bndbox>
		</object>
		<object>
			<name>face</name>
			<pose>Unspecified</pose>
			<truncated>0</truncated>
			<difficult>0</difficult>
			<bndbox>
				<xmin>332</xmin>
				<ymin>208</ymin>
				<xmax>384</xmax>
				<ymax>264</ymax>
			</bndbox>
		</object>
		<object>
			<name>face</name>
			<pose>Unspecified</pose>
			<truncated>0</truncated>
			<difficult>0</difficult>
			<bndbox>
				<xmin>370</xmin>
				<ymin>145</ymin>
				<xmax>438</xmax>
				<ymax>236</ymax>
			</bndbox>
		</object>
	</annotation>
