<annotation>
	<folder>nwafu_sheep_face2</folder>
	<filename>1677.jpg</filename>
	<path>D:\Tencent Files\799009642\FileRecv\data\data\nwafu_sheep_face2\1677.jpg</path>
	<source>
		<database>Unknown</database>
	</source>
	<size>
		<width>641</width>
		<height>401</height>
		<depth>3</depth>
	</size>
	<segmented>0</segmented>
	<object>
		<name>face</name>
		<pose>Unspecified</pose>
		<truncated>0</truncated>
		<difficult>0</difficult>
		<bndbox>
			<xmin>386</xmin>
			<ymin>50</ymin>
			<xmax>449</xmax>
			<ymax>153</ymax>
		</bndbox>
	</object>
	<object>
		<name>face</name>
		<pose>Unspecified</pose>
		<truncated>0</truncated>
		<difficult>0</difficult>
		<bndbox>
			<xmin>506</xmin>
			<ymin>235</ymin>
			<xmax>551</xmax>
			<ymax>320</ymax>
		</bndbox>
	</object>
</annotation>
