<annotation>
	<folder>nwafu_sheep_face2</folder>
	<filename>1822.jpg</filename>
	<path>D:\Tencent Files\799009642\FileRecv\data\data\nwafu_sheep_face2\1822.jpg</path>
	<source>
		<database>Unknown</database>
	</source>
	<size>
		<width>448</width>
		<height>299</height>
		<depth>3</depth>
	</size>
	<segmented>0</segmented>
	<object>
		<name>face</name>
		<pose>Unspecified</pose>
		<truncated>0</truncated>
		<difficult>0</difficult>
		<bndbox>
			<xmin>238</xmin>
			<ymin>127</ymin>
			<xmax>321</xmax>
			<ymax>243</ymax>
		</bndbox>
	</object>
</annotation>
