<annotation>
	<folder>nwafu_sheep_face2</folder>
	<filename>2153.jpg</filename>
	<path>D:\Tencent Files\799009642\FileRecv\data\data\nwafu_sheep_face2\2153.jpg</path>
	<source>
		<database>Unknown</database>
	</source>
	<size>
		<width>500</width>
		<height>500</height>
		<depth>3</depth>
	</size>
	<segmented>0</segmented>
	<object>
		<name>face</name>
		<pose>Unspecified</pose>
		<truncated>0</truncated>
		<difficult>0</difficult>
		<bndbox>
			<xmin>69</xmin>
			<ymin>63</ymin>
			<xmax>155</xmax>
			<ymax>165</ymax>
		</bndbox>
	</object>
</annotation>
