<annotation>
	<folder>nwafu_sheep_face2</folder>
	<filename>2434.jpg</filename>
	<path>D:\Tencent Files\799009642\FileRecv\data\data\nwafu_sheep_face2\2434.jpg</path>
	<source>
		<database>Unknown</database>
	</source>
	<size>
		<width>650</width>
		<height>297</height>
		<depth>3</depth>
	</size>
	<segmented>0</segmented>
	<object>
		<name>face</name>
		<pose>Unspecified</pose>
		<truncated>0</truncated>
		<difficult>0</difficult>
		<bndbox>
			<xmin>190</xmin>
			<ymin>73</ymin>
			<xmax>343</xmax>
			<ymax>290</ymax>
		</bndbox>
	</object>
	<object>
		<name>face</name>
		<pose>Unspecified</pose>
		<truncated>0</truncated>
		<difficult>0</difficult>
		<bndbox>
			<xmin>306</xmin>
			<ymin>47</ymin>
			<xmax>422</xmax>
			<ymax>259</ymax>
		</bndbox>
	</object>
</annotation>
