<annotation>
	<folder>nwafu_sheep_face2</folder>
	<filename>2904.jpg</filename>
	<path>C:\Users\XuLiu\Desktop\nwafu_sheep_face2\2904.jpg</path>
	<source>
		<database>Unknown</database>
	</source>
	<size>
		<width>500</width>
		<height>332</height>
		<depth>3</depth>
	</size>
	<segmented>0</segmented>
	<object>
		<name>face</name>
		<pose>Unspecified</pose>
		<truncated>0</truncated>
		<difficult>0</difficult>
		<bndbox>
			<xmin>201</xmin>
			<ymin>155</ymin>
			<xmax>221</xmax>
			<ymax>184</ymax>
		</bndbox>
	</object>
	<object>
		<name>face</name>
		<pose>Unspecified</pose>
		<truncated>0</truncated>
		<difficult>0</difficult>
		<bndbox>
			<xmin>226</xmin>
			<ymin>161</ymin>
			<xmax>245</xmax>
			<ymax>191</ymax>
		</bndbox>
	</object>
	<object>
		<name>face</name>
		<pose>Unspecified</pose>
		<truncated>0</truncated>
		<difficult>0</difficult>
		<bndbox>
			<xmin>368</xmin>
			<ymin>162</ymin>
			<xmax>385</xmax>
			<ymax>187</ymax>
		</bndbox>
	</object>
</annotation>
