<annotation>
	<folder>nwafu_sheep_face2</folder>
	<filename>3441.jpg</filename>
	<path>C:\Users\XuLiu\Desktop\nwafu_sheep_face2\3441.jpg</path>
	<source>
		<database>Unknown</database>
	</source>
	<size>
		<width>500</width>
		<height>333</height>
		<depth>3</depth>
	</size>
	<segmented>0</segmented>
	<object>
		<name>face</name>
		<pose>Unspecified</pose>
		<truncated>0</truncated>
		<difficult>0</difficult>
		<bndbox>
			<xmin>170</xmin>
			<ymin>92</ymin>
			<xmax>214</xmax>
			<ymax>149</ymax>
		</bndbox>
	</object>
	<object>
		<name>face</name>
		<pose>Unspecified</pose>
		<truncated>0</truncated>
		<difficult>0</difficult>
		<bndbox>
			<xmin>230</xmin>
			<ymin>57</ymin>
			<xmax>265</xmax>
			<ymax>103</ymax>
		</bndbox>
	</object>
	<object>
		<name>face</name>
		<pose>Unspecified</pose>
		<truncated>0</truncated>
		<difficult>0</difficult>
		<bndbox>
			<xmin>412</xmin>
			<ymin>109</ymin>
			<xmax>448</xmax>
			<ymax>165</ymax>
		</bndbox>
	</object>
</annotation>
